insdc_benchmarking_scripts/__init__.py
insdc_benchmarking_scripts/examples/run_benchmark.sh
insdc_benchmarking_scripts/scripts/__init__.py
insdc_benchmarking_scripts/scripts/benchmark_ftp.py
insdc_benchmarking_scripts/scripts/benchmark_http.py
insdc_benchmarking_scripts/utils/__init__.py
insdc_benchmarking_scripts/utils/config.py
insdc_benchmarking_scripts/utils/network_baseline.py
insdc_benchmarking_scripts/utils/repositories/__init__.py
insdc_benchmarking_scripts/utils/repositories/ddbj_repo.py
insdc_benchmarking_scripts/utils/repositories/ena_repo.py
insdc_benchmarking_scripts/utils/repositories/sra_repo.py
insdc_benchmarking_scripts/utils/submit.py
insdc_benchmarking_scripts/utils/system_metrics.py
insdc_benchmarking_scripts-0.1.9.dist-info/METADATA
insdc_benchmarking_scripts-0.1.9.dist-info/WHEEL
insdc_benchmarking_scripts-0.1.9.dist-info/entry_points.txt
insdc_benchmarking_scripts-0.1.9.dist-info/RECORD
