Metadata-Version: 2.1
Name: insdc-benchmarking-scripts
Version: 0.1.9
Summary: Benchmarking scripts for INSDC data transfers
License: Apache-2.0
Keywords: INSDC,benchmark,ENA,SRA,FTP,HTTP
Author: Australian BioCommons
Author-email: guerdon@biocommons.org.au
Requires-Python: >=3.9,<4.0
Classifier: Environment :: Console
Classifier: License :: OSI Approved :: Apache Software License
Classifier: Programming Language :: Python :: 3
Classifier: Programming Language :: Python :: 3.9
Classifier: Programming Language :: Python :: 3.10
Classifier: Programming Language :: Python :: 3.11
Classifier: Programming Language :: Python :: 3.12
Classifier: Topic :: Internet
Requires-Dist: certifi (>=2025.10.5,<2026.0.0)
Requires-Dist: click (>=8.1.0,<9.0.0)
Requires-Dist: insdc-benchmarking-schema (>=1.2.0,<2.0.0)
Requires-Dist: psutil (>=5.9.0,<6.0.0)
Requires-Dist: pyyaml (>=6.0.0,<7.0.0)
Requires-Dist: requests (>=2.31.0,<3.0.0)
